fvisionNetwork14/__init__.py
fvisionNetwork14/__main__.py
fvisionNetwork14/add_two_number.py
fvisionNetwork14/fvNet14.py
fvisionNetwork14/image_pre_processing.py
fvisionNetwork14/image_preprocessing.py
fvisionNetwork14/plot_acuracy.py
fvisionNetwork14/plot_loss.py
fvisionNetwork14/plot_model_acuracy.py
fvisionNetwork14/plot_model_loss.py
fvisionNetwork14-0.0.11.dist-info/LICENSE
fvisionNetwork14-0.0.11.dist-info/METADATA
fvisionNetwork14-0.0.11.dist-info/WHEEL
fvisionNetwork14-0.0.11.dist-info/top_level.txt
fvisionNetwork14-0.0.11.dist-info/RECORD
