Metadata-Version: 2.1
Name: fvisionNetwork14
Version: 0.0.11
Summary: fvisionNetwork14 is an image classification CNN model that can classify the  number of classes.
Home-page: https://github.com/KalyanMohanty/fvisionNetwork14
Author: Kalyan Mohanty
Author-email: kalyanrisingstar@gmail.com
License: MIT
Keywords: fvisionNetwork14,fvNet14,image classification,deep neural network,cnn,keras model,cnn
Platform: UNKNOWN
Classifier: Intended Audience :: Science/Research
Classifier: Intended Audience :: Education
Classifier: License :: OSI Approved :: MIT License
Classifier: Programming Language :: Python :: 3.10
Classifier: Programming Language :: Python :: 3.9
Classifier: Programming Language :: Python :: 3.8
Requires-Dist: matplotlib
Requires-Dist: numpy
